<Metadata>
  <DumpFile>CHEAPSKATE-1000</DumpFile>
  <DumpFileLoadAddress>$0400</DumpFileLoadAddress>
  <DumpFileSHA1>f62f05798023235cb7469abb90cd0251173b6f95</DumpFileSHA1>
  <JumpAddresses>
    <Address>$1000</Address>
  </JumpAddresses>
  <UseBasicRun>0</UseBasicRun>
  <InterruptsEnabled>1</InterruptsEnabled>
  <MemoryConfig>$36</MemoryConfig>
  <LoadingScreenBorderColour>0</LoadingScreenBorderColour>
  <SourceFile>Cheap Skate.tap</SourceFile>
  <SourceFileSHA1>5353c27226041c0ddb2ba2204f0c878d7a8bbfd6</SourceFileSHA1>
  <ExomizerCommand>exomizer sfx 0x1000 "CHEAPSKATE-1000" -Di_irq_exit=1 -s "inc $d030 lsr $d011" -f "w1: bit $d011 bpl w1 w2: bit $d011 bmi w2 jsr $fda3 rol $d011 lda #$36 sta $01 dec $d030" -x "inc $d020" -o "Cheap Skate.prg"</ExomizerCommand>
</Metadata>