<Metadata>
  <DumpFile>COMMANDO-0850</DumpFile>
  <DumpFileLoadAddress>$0400</DumpFileLoadAddress>
  <DumpFileSHA1>f7c0b784e25303d0f259f3774f82c7ad98089ade</DumpFileSHA1>
  <JumpAddresses>
    <Address>$0850</Address>
  </JumpAddresses>
  <UseBasicRun>0</UseBasicRun>
  <InterruptsEnabled>1</InterruptsEnabled>
  <MemoryConfig>$37</MemoryConfig>
  <RasterBarType>FreeLoad</RasterBarType>
  <SidLength>65</SidLength>
  <SourceFile>Commando.tap</SourceFile>
  <SourceFileSHA1>a5640ed9a29d39a4bcaf22446794ac84b3c68cda</SourceFileSHA1>
  <ExomizerCommand>exomizer sfx 0x0850 "COMMANDO-0850" -Di_irq_exit=1 -s "inc $d030 lsr $d011" -f "w1: bit $d011 bpl w1 w2: bit $d011 bmi w2 jsr $fda3 rol $d011 dec $d030" -x "inc $d020" -o "Commando.prg"</ExomizerCommand>
  <Notes>As the original did not have a loading screen, the one included was converted from the Spectrum version by DATA-LAND of Technische Maschinenfabrik (https://csdb.dk/scener/?id=4845).</Notes>
</Metadata>