<Metadata>
  <DumpFile>DEMONSOFTOPAZ-9047</DumpFile>
  <DumpFileLoadAddress>$0400</DumpFileLoadAddress>
  <DumpFileSHA1>387122476a5411e691ee6d0fc1f06025f9036af0</DumpFileSHA1>
  <JumpAddresses>
    <Address>$9047</Address>
  </JumpAddresses>
  <UseBasicRun>0</UseBasicRun>
  <InterruptsEnabled>1</InterruptsEnabled>
  <MemoryConfig>$37</MemoryConfig>
  <SourceFile>Demons of Topaz - Ozzy Versus The Universe.tap</SourceFile>
  <SourceFileSHA1>53b35dff53447af8ba5d5edf03f2a515ff61999f</SourceFileSHA1>
  <ExomizerCommand>exomizer sfx 0x9047 "DEMONSOFTOPAZ-9047" -Di_irq_exit=1 -s "inc $d030 lsr $d011" -f "w1: bit $d011 bpl w1 w2: bit $d011 bmi w2 jsr $fda3 rol $d011 dec $d030" -x "inc $d020" -o "Demons of Topaz - Ozzy Versus The Universe.prg"</ExomizerCommand>
</Metadata>