<Metadata>
  <DumpFile>DONALDDUCKSPLAYGROUND-0811</DumpFile>
  <DumpFileLoadAddress>$0400</DumpFileLoadAddress>
  <DumpFileSHA1>06ea8344be0884a05fc590367315a0832e75b17e</DumpFileSHA1>
  <JumpAddresses>
    <Address>$0811</Address>
  </JumpAddresses>
  <UseBasicRun>1</UseBasicRun>
  <InterruptsEnabled>1</InterruptsEnabled>
  <MemoryConfig>$37</MemoryConfig>
  <LoadingScreenBorderColour>0</LoadingScreenBorderColour>
  <SourceFile>Donald Duck's Playground.tap</SourceFile>
  <SourceFileSHA1>6fe3eeca3acefa993ccfceef0960437b05fe53ff</SourceFileSHA1>
  <ExomizerCommand>exomizer sfx basic,$0801,$ffff "DONALDDUCKSPLAYGROUND-0811" -Di_irq_exit=1 -s "inc $d030 lsr $d011" -f "w1: bit $d011 bpl w1 w2: bit $d011 bmi w2 jsr $fda3 rol $d011 dec $d030" -x "inc $d020" -o "Donald Duck's Playground.prg"</ExomizerCommand>
  <Notes>The loading screen is from the disk version</Notes>
</Metadata>