<Metadata>
  <DumpFile>PROFESSIONALBMXSIMULATOR-EXPERT-DIRT-1000</DumpFile>
  <DumpFileLoadAddress>$0400</DumpFileLoadAddress>
  <DumpFileSHA1>723659ca5a375cbae7821456a09f213e9bffc352</DumpFileSHA1>
  <JumpAddresses>
    <Address>$1000</Address>
  </JumpAddresses>
  <UseBasicRun>0</UseBasicRun>
  <InterruptsEnabled>1</InterruptsEnabled>
  <MemoryConfig>$36</MemoryConfig>
  <LoadingScreenBorderColour>0</LoadingScreenBorderColour>
  <SourceFile>Professional BMX Simulator (Expert - Dirt).tap</SourceFile>
  <SourceFileSHA1>fe53ae83490b7c463c1f4aad36e9a0e785fb297f</SourceFileSHA1>
  <ExomizerCommand>exomizer sfx 0x1000 "PROFESSIONALBMXSIMULATOR-EXPERT-DIRT-1000" -Di_irq_exit=1 -s "inc $d030 lsr $d011" -f "w1: bit $d011 bpl w1 w2: bit $d011 bmi w2 jsr $fda3 rol $d011 lda #$36 sta $01 dec $d030" -x "inc $d020" -o "Professional BMX Simulator (Expert - Dirt).prg"</ExomizerCommand>
</Metadata>