<Metadata>
  <DumpFile>SNODGITS-0DFB</DumpFile>
  <DumpFileLoadAddress>$0400</DumpFileLoadAddress>
  <DumpFileSHA1>38cc534d2c19fb57d25bf7dac681fa41d3b19ecf</DumpFileSHA1>
  <JumpAddresses>
    <Address>$0DFB</Address>
  </JumpAddresses>
  <UseBasicRun>0</UseBasicRun>
  <InterruptsEnabled>0</InterruptsEnabled>
  <MemoryConfig>$35</MemoryConfig>
  <LoadingScreenBorderColour>0</LoadingScreenBorderColour>
  <PrimaryControlType>JoystickPort1</PrimaryControlType>
  <SourceFile>Snodgits.tap</SourceFile>
  <SourceFileSHA1>975a9c10607fda4391c2ad92dd82e1a79a78902d</SourceFileSHA1>
  <ExomizerCommand>exomizer sfx 0x0DFB "SNODGITS-0DFB" -Di_irq_exit=0 -s "inc $d030 lsr $d011" -f "w1: bit $d011 bpl w1 w2: bit $d011 bmi w2 jsr $fda3 rol $d011 lda #$35 sta $01 dec $d030" -x "inc $d020" -o "Snodgits (J1).prg"</ExomizerCommand>
</Metadata>