<Metadata>
  <DumpFile>WATERSKI3D-4000</DumpFile>
  <DumpFileLoadAddress>$0400</DumpFileLoadAddress>
  <DumpFileSHA1>6f2bfbdd337c98f103f9a12d1a40a12275c3d28b</DumpFileSHA1>
  <JumpAddresses>
    <Address>$4000</Address>
  </JumpAddresses>
  <UseBasicRun>0</UseBasicRun>
  <InterruptsEnabled>1</InterruptsEnabled>
  <MemoryConfig>$37</MemoryConfig>
  <SourceFile>Waterski 3D.tap</SourceFile>
  <SourceFileSHA1>baffc045dca459781f79f89f53194f0924290244</SourceFileSHA1>
  <ExomizerCommand>exomizer sfx 0x4000 "WATERSKI3D-4000" -Di_irq_exit=1 -s "inc $d030 lsr $d011" -f "w1: bit $d011 bpl w1 w2: bit $d011 bmi w2 jsr $fda3 rol $d011 dec $d030" -x "inc $d020" -o "Waterski 3D.prg"</ExomizerCommand>
</Metadata>