<Metadata>
  <DumpFile>ZOMPYSTOMP-080D</DumpFile>
  <DumpFileLoadAddress>$0400</DumpFileLoadAddress>
  <DumpFileSHA1>b18c265a972daaea991afe2a38f0c756fd8b7681</DumpFileSHA1>
  <SimplifiedName>Zompy Stomp</SimplifiedName>
  <JumpAddresses>
    <Address>$080D</Address>
  </JumpAddresses>
  <UseBasicRun>1</UseBasicRun>
  <InterruptsEnabled>1</InterruptsEnabled>
  <MemoryConfig>$37</MemoryConfig>
  <SourceFile>Zompy Stomp (Blast Collection #13).d64</SourceFile>
  <SourceFileSHA1>f788d8188e20b2bae393e53e18c2645f24292082</SourceFileSHA1>
  <ExomizerCommand>exomizer sfx basic,$0801,$ffff "ZOMPYSTOMP-080D" -Di_irq_exit=1 -s "inc $d030 lsr $d011" -f "w1: bit $d011 bpl w1 w2: bit $d011 bmi w2 jsr $fda3 rol $d011 dec $d030" -x "inc $d020" -o "Zompy Stomp.prg"</ExomizerCommand>
</Metadata>